marketdl/__init__.py
marketdl/__main__.py
marketdl/cli.py
marketdl/config.py
marketdl/containers.py
marketdl/coordinator.py
marketdl/interfaces.py
marketdl/logger.py
marketdl/market_data.py
marketdl/models.py
marketdl/progress.py
marketdl/storage.py
marketdl/utils.py
marketdl/worker.py
marketdl-0.1.1.dist-info/LICENSE
marketdl-0.1.1.dist-info/METADATA
marketdl-0.1.1.dist-info/WHEEL
marketdl-0.1.1.dist-info/entry_points.txt
marketdl-0.1.1.dist-info/top_level.txt
marketdl-0.1.1.dist-info/RECORD
