Metadata-Version: 2.1
Name: marketdl
Version: 0.1.1
Summary: Reproducible market data downloader
Home-page: https://github.com/asirenius/marketdl
Author: asirenius
License: MIT
Classifier: License :: OSI Approved :: MIT License
Classifier: Programming Language :: Python :: 3
Requires-Python: >=3.10
License-File: LICENSE
Requires-Dist: typer >=0.9.0
Requires-Dist: pydantic >=2.0.0
Requires-Dist: PyYAML >=6.0.0
Requires-Dist: pandas >=2.0.0
Requires-Dist: pyarrow >=14.0.1
Requires-Dist: httpx >=0.25.0
Requires-Dist: dependency-injector >=4.41.0
Requires-Dist: rich >=13.0.0
Requires-Dist: aiofiles >=23.0.0
Requires-Dist: pytest >=7.0.0
Requires-Dist: pytest-asyncio >=0.21.0
